[ {
  "sourceURL" : "http://docs.aws.amazon.com/AWSCloudFormation/latest/UserGuide/aws-properties-cloudfront-distribution.html",
  "resourceType" : "AWS::CloudFront::Distribution",
  "properties" : [ {
    "propertyName" : "DistributionConfig",
    "propertyType" : "AWS::CloudFront::Distribution::DistributionConfig",
    "propertyHref" : "aws-properties-cloudfront-distributionconfig.html",
    "required" : true
  } ]
}, {
  "sourceURL" : "http://docs.aws.amazon.com/AWSCloudFormation/latest/UserGuide/aws-properties-cloudfront-distributionconfig.html",
  "resourceType" : "AWS::CloudFront::Distribution::DistributionConfig",
  "properties" : [ {
    "propertyName" : "Aliases",
    "propertyType" : "List<String>",
    "required" : false
  }, {
    "propertyName" : "CacheBehaviors",
    "propertyType" : "List<AWS::CloudFront::Distribution::DistributionConfig::CacheBehavior>",
    "propertyHref" : "aws-properties-cloudfront-cachebehavior.html",
    "required" : false
  }, {
    "propertyName" : "Comment",
    "propertyType" : "String",
    "required" : false
  }, {
    "propertyName" : "CustomErrorResponses",
    "propertyType" : "List<AWS::CloudFront::Distribution::DistributionConfig::CustomErrorResponse>",
    "propertyHref" : "aws-properties-cloudfront-distributionconfig-customerrorresponse.html",
    "required" : false
  }, {
    "propertyName" : "DefaultCacheBehavior",
    "propertyType" : "AWS::CloudFront::Distribution::DistributionConfig::DefaultCacheBehavior",
    "propertyHref" : "aws-properties-cloudfront-defaultcachebehavior.html",
    "required" : true
  }, {
    "propertyName" : "DefaultRootObject",
    "propertyType" : "String",
    "required" : false
  }, {
    "propertyName" : "Enabled",
    "propertyType" : "Boolean",
    "required" : true
  }, {
    "propertyName" : "HttpVersion",
    "propertyType" : "String",
    "required" : false
  }, {
    "propertyName" : "Logging",
    "propertyType" : "AWS::CloudFront::Distribution::DistributionConfig::Logging",
    "propertyHref" : "aws-properties-cloudfront-logging.html",
    "required" : false
  }, {
    "propertyName" : "Origins",
    "propertyType" : "List<AWS::CloudFront::Distribution::DistributionConfig::Origin>",
    "propertyHref" : "aws-properties-cloudfront-origin.html",
    "required" : true
  }, {
    "propertyName" : "PriceClass",
    "propertyType" : "String",
    "required" : false
  }, {
    "propertyName" : "Restrictions",
    "propertyType" : "AWS::CloudFront::Distribution::DistributionConfig::Restriction",
    "propertyHref" : "aws-properties-cloudfront-distributionconfig-restrictions.html",
    "required" : false
  }, {
    "propertyName" : "ViewerCertificate",
    "propertyType" : "AWS::CloudFront::Distribution::DistributionConfig::ViewerCertificate",
    "propertyHref" : "aws-properties-cloudfront-distributionconfig-viewercertificate.html",
    "required" : false
  }, {
    "propertyName" : "WebACLId",
    "propertyType" : "String",
    "required" : false
  } ]
}, {
  "sourceURL" : "http://docs.aws.amazon.com/AWSCloudFormation/latest/UserGuide/aws-properties-cloudfront-cachebehavior.html",
  "resourceType" : "AWS::CloudFront::Distribution::DistributionConfig::CacheBehavior",
  "properties" : [ {
    "propertyName" : "AllowedMethods",
    "propertyType" : "List<String>",
    "required" : false
  }, {
    "propertyName" : "CachedMethods",
    "propertyType" : "List<String>",
    "required" : false
  }, {
    "propertyName" : "Compress",
    "propertyType" : "Boolean",
    "required" : false
  }, {
    "propertyName" : "DefaultTTL",
    "propertyType" : "Number",
    "required" : false
  }, {
    "propertyName" : "ForwardedValues",
    "propertyType" : "AWS::CloudFront::Distribution::DistributionConfig::DefaultCacheBehavior::ForwardedValue",
    "propertyHref" : "aws-properties-cloudfront-forwardedvalues.html",
    "required" : true
  }, {
    "propertyName" : "MaxTTL",
    "propertyType" : "Number",
    "required" : false
  }, {
    "propertyName" : "MinTTL",
    "propertyType" : "Number",
    "required" : false
  }, {
    "propertyName" : "PathPattern",
    "propertyType" : "String",
    "required" : true
  }, {
    "propertyName" : "SmoothStreaming",
    "propertyType" : "Boolean",
    "required" : false
  }, {
    "propertyName" : "TargetOriginId",
    "propertyType" : "String",
    "required" : true
  }, {
    "propertyName" : "TrustedSigners",
    "propertyType" : "List<String>",
    "required" : false
  }, {
    "propertyName" : "ViewerProtocolPolicy",
    "propertyType" : "String",
    "required" : true
  } ]
}, {
  "sourceURL" : "http://docs.aws.amazon.com/AWSCloudFormation/latest/UserGuide/aws-properties-cloudfront-forwardedvalues.html",
  "resourceType" : "AWS::CloudFront::Distribution::DistributionConfig::DefaultCacheBehavior::ForwardedValue",
  "properties" : [ {
    "propertyName" : "Cookies",
    "propertyType" : "AWS::CloudFront::Distribution::DistributionConfig::DefaultCacheBehavior::ForwardedValue::Cooky",
    "propertyHref" : "aws-properties-cloudfront-forwardedvalues-cookies.html",
    "required" : false
  }, {
    "propertyName" : "Headers",
    "propertyType" : "List<String>",
    "required" : false
  }, {
    "propertyName" : "QueryString",
    "propertyType" : "Boolean",
    "required" : true
  }, {
    "propertyName" : "QueryStringCacheKeys",
    "propertyType" : "List<String>",
    "required" : false
  } ]
}, {
  "sourceURL" : "http://docs.aws.amazon.com/AWSCloudFormation/latest/UserGuide/aws-properties-cloudfront-forwardedvalues-cookies.html",
  "resourceType" : "AWS::CloudFront::Distribution::DistributionConfig::DefaultCacheBehavior::ForwardedValue::Cooky",
  "properties" : [ {
    "propertyName" : "Forward",
    "propertyType" : "String",
    "required" : true
  }, {
    "propertyName" : "WhitelistedNames",
    "propertyType" : "List<String>",
    "required" : false
  } ]
}, {
  "sourceURL" : "http://docs.aws.amazon.com/AWSCloudFormation/latest/UserGuide/aws-properties-cloudfront-distributionconfig-customerrorresponse.html",
  "resourceType" : "AWS::CloudFront::Distribution::DistributionConfig::CustomErrorResponse",
  "properties" : [ {
    "propertyName" : "ErrorCachingMinTTL",
    "propertyType" : "Number",
    "required" : false
  }, {
    "propertyName" : "ErrorCode",
    "propertyType" : "Number",
    "required" : true
  }, {
    "propertyName" : "ResponseCode",
    "propertyType" : "Number",
    "required" : false
  }, {
    "propertyName" : "ResponsePagePath",
    "propertyType" : "String",
    "required" : false
  } ]
}, {
  "sourceURL" : "http://docs.aws.amazon.com/AWSCloudFormation/latest/UserGuide/aws-properties-cloudfront-defaultcachebehavior.html",
  "resourceType" : "AWS::CloudFront::Distribution::DistributionConfig::DefaultCacheBehavior",
  "properties" : [ {
    "propertyName" : "AllowedMethods",
    "propertyType" : "List<String>",
    "required" : false
  }, {
    "propertyName" : "CachedMethods",
    "propertyType" : "List<String>",
    "required" : false
  }, {
    "propertyName" : "Compress",
    "propertyType" : "Boolean",
    "required" : false
  }, {
    "propertyName" : "DefaultTTL",
    "propertyType" : "Number",
    "required" : false
  }, {
    "propertyName" : "ForwardedValues",
    "propertyType" : "AWS::CloudFront::Distribution::DistributionConfig::DefaultCacheBehavior::ForwardedValue",
    "propertyHref" : "aws-properties-cloudfront-forwardedvalues.html",
    "required" : true
  }, {
    "propertyName" : "MaxTTL",
    "propertyType" : "Number",
    "required" : false
  }, {
    "propertyName" : "MinTTL",
    "propertyType" : "String",
    "required" : false
  }, {
    "propertyName" : "SmoothStreaming",
    "propertyType" : "Boolean",
    "required" : false
  }, {
    "propertyName" : "TargetOriginId",
    "propertyType" : "String",
    "required" : true
  }, {
    "propertyName" : "TrustedSigners",
    "propertyType" : "List<String>",
    "required" : false
  }, {
    "propertyName" : "ViewerProtocolPolicy",
    "propertyType" : "String",
    "required" : true
  } ]
}, {
  "sourceURL" : "http://docs.aws.amazon.com/AWSCloudFormation/latest/UserGuide/aws-properties-cloudfront-logging.html",
  "resourceType" : "AWS::CloudFront::Distribution::DistributionConfig::Logging",
  "properties" : [ {
    "propertyName" : "Bucket",
    "propertyType" : "String",
    "required" : true
  }, {
    "propertyName" : "IncludeCookies",
    "propertyType" : "Boolean",
    "required" : false
  }, {
    "propertyName" : "Prefix",
    "propertyType" : "String",
    "required" : false
  } ]
}, {
  "sourceURL" : "http://docs.aws.amazon.com/AWSCloudFormation/latest/UserGuide/aws-properties-cloudfront-origin.html",
  "resourceType" : "AWS::CloudFront::Distribution::DistributionConfig::Origin",
  "properties" : [ {
    "propertyName" : "CustomOriginConfig",
    "propertyType" : "AWS::CloudFront::Distribution::DistributionConfig::Origin::CustomOrigin",
    "propertyHref" : "aws-properties-cloudfront-customorigin.html",
    "required" : false
  }, {
    "propertyName" : "DomainName",
    "propertyType" : "String",
    "required" : true
  }, {
    "propertyName" : "Id",
    "propertyType" : "String",
    "required" : true
  }, {
    "propertyName" : "OriginCustomHeaders",
    "propertyType" : "List<AWS::CloudFront::Distribution::DistributionConfig::Origin::OriginCustomHeader>",
    "propertyHref" : "aws-properties-cloudfront-origin-origincustomheader.html",
    "required" : false
  }, {
    "propertyName" : "OriginPath",
    "propertyType" : "String",
    "required" : false
  }, {
    "propertyName" : "S3OriginConfig",
    "propertyType" : "AWS::CloudFront::Distribution::DistributionConfig::Origin::S3Origin",
    "propertyHref" : "aws-properties-cloudfront-s3origin.html",
    "required" : false
  } ]
}, {
  "sourceURL" : "http://docs.aws.amazon.com/AWSCloudFormation/latest/UserGuide/aws-properties-cloudfront-customorigin.html",
  "resourceType" : "AWS::CloudFront::Distribution::DistributionConfig::Origin::CustomOrigin",
  "properties" : [ {
    "propertyName" : "HTTPPort",
    "propertyType" : "Number",
    "required" : false
  }, {
    "propertyName" : "HTTPSPort",
    "propertyType" : "Number",
    "required" : false
  }, {
    "propertyName" : "OriginProtocolPolicy",
    "propertyType" : "String",
    "required" : true
  }, {
    "propertyName" : "OriginSSLProtocols",
    "propertyType" : "List<String>",
    "required" : false
  } ]
}, {
  "sourceURL" : "http://docs.aws.amazon.com/AWSCloudFormation/latest/UserGuide/aws-properties-cloudfront-origin-origincustomheader.html",
  "resourceType" : "AWS::CloudFront::Distribution::DistributionConfig::Origin::OriginCustomHeader",
  "properties" : [ {
    "propertyName" : "HeaderName",
    "propertyType" : "String",
    "required" : true
  }, {
    "propertyName" : "HeaderValue",
    "propertyType" : "String",
    "required" : true
  } ]
}, {
  "sourceURL" : "http://docs.aws.amazon.com/AWSCloudFormation/latest/UserGuide/aws-properties-cloudfront-s3origin.html",
  "resourceType" : "AWS::CloudFront::Distribution::DistributionConfig::Origin::S3Origin",
  "properties" : [ {
    "propertyName" : "OriginAccessIdentity",
    "propertyType" : "String",
    "required" : false
  } ]
}, {
  "sourceURL" : "http://docs.aws.amazon.com/AWSCloudFormation/latest/UserGuide/aws-properties-cloudfront-distributionconfig-restrictions.html",
  "resourceType" : "AWS::CloudFront::Distribution::DistributionConfig::Restriction",
  "properties" : [ {
    "propertyName" : "GeoRestriction",
    "propertyType" : "AWS::CloudFront::Distribution::DistributionConfig::Restriction::GeoRestriction",
    "propertyHref" : "aws-properties-cloudfront-distributionconfig-restrictions-georestriction.html",
    "required" : true
  } ]
}, {
  "sourceURL" : "http://docs.aws.amazon.com/AWSCloudFormation/latest/UserGuide/aws-properties-cloudfront-distributionconfig-restrictions-georestriction.html",
  "resourceType" : "AWS::CloudFront::Distribution::DistributionConfig::Restriction::GeoRestriction",
  "properties" : [ {
    "propertyName" : "Locations",
    "propertyType" : "List<String>",
    "required" : false
  }, {
    "propertyName" : "RestrictionType",
    "propertyType" : "String",
    "required" : true
  } ]
}, {
  "sourceURL" : "http://docs.aws.amazon.com/AWSCloudFormation/latest/UserGuide/aws-properties-cloudfront-distributionconfig-viewercertificate.html",
  "resourceType" : "AWS::CloudFront::Distribution::DistributionConfig::ViewerCertificate",
  "properties" : [ {
    "propertyName" : "AcmCertificateArn",
    "propertyType" : "String",
    "required" : false
  }, {
    "propertyName" : "CloudFrontDefaultCertificate",
    "propertyType" : "Boolean",
    "required" : false
  }, {
    "propertyName" : "IamCertificateId",
    "propertyType" : "String",
    "required" : false
  }, {
    "propertyName" : "MinimumProtocolVersion",
    "propertyType" : "String",
    "required" : false
  }, {
    "propertyName" : "SslSupportMethod",
    "propertyType" : "String",
    "required" : false
  } ]
} ]